octopus_openapi_util/__init__.py
octopus_openapi_util/authorization.py
octopus_openapi_util-0.0.1.dist-info/LICENSE
octopus_openapi_util-0.0.1.dist-info/METADATA
octopus_openapi_util-0.0.1.dist-info/WHEEL
octopus_openapi_util-0.0.1.dist-info/top_level.txt
octopus_openapi_util-0.0.1.dist-info/RECORD
